metaip/__init__.py
metaip/__main__.py
metaip/cli.py
metaip/exceptions.py
metaip/metaip.py
metaip/resources/__init__.py
metaip-0.1.0.dist-info/LICENSE
metaip-0.1.0.dist-info/METADATA
metaip-0.1.0.dist-info/WHEEL
metaip-0.1.0.dist-info/entry_points.txt
metaip-0.1.0.dist-info/top_level.txt
metaip-0.1.0.dist-info/RECORD
