Metadata-Version: 2.1
Name: metaip
Version: 0.1.0
Summary: Return the latitude and longitude associated with an IP address
Home-page: https://github.com/Stephen-RA-King/metaip
Download-URL: https://github.com/Stephen-RA-King/metaip/archive/refs/heads/main.zip
Author: Stephen R A King
Author-email: sking.github@gmail.com
Maintainer: Stephen R A King
Maintainer-email: sking.github@gmail.com
License: MIT
Project-URL: Bug Tracker, https://github.com/Stephen-RA-King/metaip/issues
Project-URL: CI, https://github.com/Stephen-RA-King/metaip/actions
Project-URL: Documentation, https://metaip.readthedocs.io/en/latest/
Project-URL: Release Notes, https://github.com/Stephen-RA-King/metaip/releases
Project-URL: Source Code, https://github.com/Stephen-RA-King/metaip/
Keywords: utility
Platform: Any
Classifier: Development Status :: 1 - Planning
Classifier: Environment :: Console
Classifier: Intended Audience :: Developers
Classifier: Operating System :: OS Independent
Classifier: Natural Language :: English
Classifier: Programming Language :: Python :: 3
Classifier: Programming Language :: Python :: 3 :: Only
Classifier: Programming Language :: Python :: 3.8
Classifier: Programming Language :: Python :: 3.9
Classifier: Programming Language :: Python :: 3.10
Classifier: Programming Language :: Python :: 3.11
Classifier: Programming Language :: Python :: 3.12
Requires-Python: >=3.8
License-File: LICENSE
Requires-Dist: requests >=2.30.0
Requires-Dist: keyring >=24.2.0
Requires-Dist: pyyaml >=6.0.1
Requires-Dist: requests >=2.31.0
Requires-Dist: keyrings.alt >=5.0.0
